aioscryfall/__init__.py
aioscryfall/_version.py
aioscryfall/client.py
aioscryfall/errors.py
aioscryfall/py.typed
aioscryfall/api/__init__.py
aioscryfall/api/bulk_data.py
aioscryfall/api/cards.py
aioscryfall/api/catalogs.py
aioscryfall/api/migrations.py
aioscryfall/api/responses.py
aioscryfall/api/rulings.py
aioscryfall/api/sets.py
aioscryfall/api/symbols.py
aioscryfall/handlers/__init__.py
aioscryfall/handlers/base.py
aioscryfall/handlers/bulk_data.py
aioscryfall/handlers/cards.py
aioscryfall/handlers/catalogs.py
aioscryfall/handlers/migrations.py
aioscryfall/handlers/rulings.py
aioscryfall/handlers/sets.py
aioscryfall/handlers/symbols.py
aioscryfall/models/__init__.py
aioscryfall/models/bulk_data.py
aioscryfall/models/cards.py
aioscryfall/models/catalogs.py
aioscryfall/models/common.py
aioscryfall/models/errors.py
aioscryfall/models/lists.py
aioscryfall/models/migrations.py
aioscryfall/models/rulings.py
aioscryfall/models/serde.py
aioscryfall/models/sets.py
aioscryfall/models/symbols.py
aioscryfall/sync/__init__.py
aioscryfall/sync/client.py
aioscryfall/sync/handlers/__init__.py
aioscryfall/sync/handlers/base.py
aioscryfall/sync/handlers/bulk_data.py
aioscryfall/sync/handlers/cards.py
aioscryfall/sync/handlers/catalogs.py
aioscryfall/sync/handlers/migrations.py
aioscryfall/sync/handlers/rulings.py
aioscryfall/sync/handlers/symbols.py
aioscryfall-0.4.2.dist-info/METADATA
aioscryfall-0.4.2.dist-info/WHEEL
aioscryfall-0.4.2.dist-info/licenses/LICENSE
aioscryfall-0.4.2.dist-info/RECORD
