Metadata-Version: 2.1
Name: aioscryfall
Version: 0.4.2
Summary: Asynchronous Python client for the Scryfall API
Project-URL: Homepage, https://github.com/gwax/aioscryfall
Project-URL: Bug Tracker, https://github.com/gwax/aioscryfall/issues
Author-email: George Leslie-Waksman <waksman@gmail.com>
License: MIT
License-File: LICENSE
Keywords: magic,mtg,scryfall
Requires-Python: >=3.11
Requires-Dist: aiohttp
Requires-Dist: aiolimiter
Requires-Dist: appdirs
Requires-Dist: msgspec
Requires-Dist: requests
Requires-Dist: requests-cache
Provides-Extra: dev
Requires-Dist: aiofiles; extra == 'dev'
Requires-Dist: aioresponses; extra == 'dev'
Requires-Dist: black; extra == 'dev'
Requires-Dist: doc8; extra == 'dev'
Requires-Dist: isort; extra == 'dev'
Requires-Dist: mypy; extra == 'dev'
Requires-Dist: pygments; extra == 'dev'
Requires-Dist: pylint; extra == 'dev'
Requires-Dist: pytest; extra == 'dev'
Requires-Dist: pytest-asyncio; extra == 'dev'
Requires-Dist: ruff; extra == 'dev'
Requires-Dist: types-aiofiles; extra == 'dev'
Requires-Dist: types-appdirs; extra == 'dev'
